TaiwandaxueLinxuanTianJiqiXuexiBijiHongseShitou/README.md
TaiwandaxueLinxuanTianJiqiXuexiBijiHongseShitou/__init__.py
TaiwandaxueLinxuanTianJiqiXuexiBijiHongseShitou/__main__.py
TaiwandaxueLinxuanTianJiqiXuexiBijiHongseShitou/file.epub
TaiwandaxueLinxuanTianJiqiXuexiBijiHongseShitou/index.html
TaiwandaxueLinxuanTianJiqiXuexiBijiHongseShitou/css/__init__.py
TaiwandaxueLinxuanTianJiqiXuexiBijiHongseShitou/css/annotations.css
TaiwandaxueLinxuanTianJiqiXuexiBijiHongseShitou/css/main.css
TaiwandaxueLinxuanTianJiqiXuexiBijiHongseShitou/css/normalize.css
TaiwandaxueLinxuanTianJiqiXuexiBijiHongseShitou/css/popup.css
TaiwandaxueLinxuanTianJiqiXuexiBijiHongseShitou/font/__init__.py
TaiwandaxueLinxuanTianJiqiXuexiBijiHongseShitou/font/fontello.eot
TaiwandaxueLinxuanTianJiqiXuexiBijiHongseShitou/font/fontello.svg
TaiwandaxueLinxuanTianJiqiXuexiBijiHongseShitou/font/fontello.ttf
TaiwandaxueLinxuanTianJiqiXuexiBijiHongseShitou/font/fontello.woff
TaiwandaxueLinxuanTianJiqiXuexiBijiHongseShitou/img/__init__.py
TaiwandaxueLinxuanTianJiqiXuexiBijiHongseShitou/img/annotator-glyph-sprite.png
TaiwandaxueLinxuanTianJiqiXuexiBijiHongseShitou/img/annotator-icon-sprite.png
TaiwandaxueLinxuanTianJiqiXuexiBijiHongseShitou/img/apple-touch-icon.png
TaiwandaxueLinxuanTianJiqiXuexiBijiHongseShitou/img/cancelfullscreen.png
TaiwandaxueLinxuanTianJiqiXuexiBijiHongseShitou/img/close.png
TaiwandaxueLinxuanTianJiqiXuexiBijiHongseShitou/img/fullscreen.png
TaiwandaxueLinxuanTianJiqiXuexiBijiHongseShitou/img/loader.gif
TaiwandaxueLinxuanTianJiqiXuexiBijiHongseShitou/img/menu-icon.png
TaiwandaxueLinxuanTianJiqiXuexiBijiHongseShitou/img/save.png
TaiwandaxueLinxuanTianJiqiXuexiBijiHongseShitou/img/saved.png
TaiwandaxueLinxuanTianJiqiXuexiBijiHongseShitou/img/settings-s.png
TaiwandaxueLinxuanTianJiqiXuexiBijiHongseShitou/img/settings.png
TaiwandaxueLinxuanTianJiqiXuexiBijiHongseShitou/img/star.png
TaiwandaxueLinxuanTianJiqiXuexiBijiHongseShitou/js/__init__.py
taiwandaxue_linxuan_tian_jiqi_xuexi_biji_hongse_shitou-2024.3.3.0.dist-info/METADATA
taiwandaxue_linxuan_tian_jiqi_xuexi_biji_hongse_shitou-2024.3.3.0.dist-info/WHEEL
taiwandaxue_linxuan_tian_jiqi_xuexi_biji_hongse_shitou-2024.3.3.0.dist-info/entry_points.txt
taiwandaxue_linxuan_tian_jiqi_xuexi_biji_hongse_shitou-2024.3.3.0.dist-info/top_level.txt
taiwandaxue_linxuan_tian_jiqi_xuexi_biji_hongse_shitou-2024.3.3.0.dist-info/RECORD
